CHANGELOG.md
LICENSE
MANIFEST.in
README.md
setup.cfg
setup.py
pip_services3_expressions/__init__.py
pip_services3_expressions.egg-info/PKG-INFO
pip_services3_expressions.egg-info/SOURCES.txt
pip_services3_expressions.egg-info/dependency_links.txt
pip_services3_expressions.egg-info/requires.txt
pip_services3_expressions.egg-info/top_level.txt
pip_services3_expressions.egg-info/zip-safe
pip_services3_expressions/calculator/CalculationStack.py
pip_services3_expressions/calculator/ExpressionCalculator.py
pip_services3_expressions/calculator/ExpressionException.py
pip_services3_expressions/calculator/SyntaxErrorCode.py
pip_services3_expressions/calculator/SyntaxException.py
pip_services3_expressions/calculator/__init__.py
pip_services3_expressions/calculator/functions/DefaultFunctionCollection.py
pip_services3_expressions/calculator/functions/DelegatedFunction.py
pip_services3_expressions/calculator/functions/FunctionCollection.py
pip_services3_expressions/calculator/functions/IFunction.py
pip_services3_expressions/calculator/functions/IFunctionCollection.py
pip_services3_expressions/calculator/functions/__init__.py
pip_services3_expressions/calculator/parsers/ExpressionParser.py
pip_services3_expressions/calculator/parsers/ExpressionToken.py
pip_services3_expressions/calculator/parsers/ExpressionTokenType.py
pip_services3_expressions/calculator/parsers/__init__.py
pip_services3_expressions/calculator/tokenizers/ExpressionNumberState.py
pip_services3_expressions/calculator/tokenizers/ExpressionQuoteState.py
pip_services3_expressions/calculator/tokenizers/ExpressionSymbolState.py
pip_services3_expressions/calculator/tokenizers/ExpressionTokenizer.py
pip_services3_expressions/calculator/tokenizers/ExpressionWordState.py
pip_services3_expressions/calculator/tokenizers/__init__.py
pip_services3_expressions/calculator/variables/IVariable.py
pip_services3_expressions/calculator/variables/IVariableCollection.py
pip_services3_expressions/calculator/variables/Variable.py
pip_services3_expressions/calculator/variables/VariableCollection.py
pip_services3_expressions/calculator/variables/__init__.py
pip_services3_expressions/csv/CsvConstant.py
pip_services3_expressions/csv/CsvQuoteState.py
pip_services3_expressions/csv/CsvSymbolState.py
